lldb_mcp_server/__init__.py
lldb_mcp_server/fastmcp_server.py
lldb_mcp_server/analysis/__init__.py
lldb_mcp_server/analysis/crash_analyzer.py
lldb_mcp_server/analysis/exploitability.py
lldb_mcp_server/models/__init__.py
lldb_mcp_server/models/breakpoint.py
lldb_mcp_server/models/execution.py
lldb_mcp_server/models/security.py
lldb_mcp_server/models/session.py
lldb_mcp_server/platform/__init__.py
lldb_mcp_server/platform/detector.py
lldb_mcp_server/platform/linux.py
lldb_mcp_server/platform/macos.py
lldb_mcp_server/platform/provider.py
lldb_mcp_server/platform/windows.py
lldb_mcp_server/session/manager.py
lldb_mcp_server/session/types.py
lldb_mcp_server/tools/__init__.py
lldb_mcp_server/tools/advanced.py
lldb_mcp_server/tools/breakpoints.py
lldb_mcp_server/tools/decorators.py
lldb_mcp_server/tools/execution.py
lldb_mcp_server/tools/inspection.py
lldb_mcp_server/tools/memory.py
lldb_mcp_server/tools/security.py
lldb_mcp_server/tools/session.py
lldb_mcp_server/tools/target.py
lldb_mcp_server/tools/watchpoints.py
lldb_mcp_server/utils/config.py
lldb_mcp_server/utils/errors.py
lldb_mcp_server/utils/logging.py
lldb_mcp_server-0.3.0.dist-info/METADATA
lldb_mcp_server-0.3.0.dist-info/WHEEL
lldb_mcp_server-0.3.0.dist-info/entry_points.txt
lldb_mcp_server-0.3.0.dist-info/top_level.txt
lldb_mcp_server-0.3.0.dist-info/RECORD
