Metadata-Version: 2.4
Name: lldb-mcp-server
Version: 0.3.0
Summary: AI-powered C/C++ debugger via LLDB and Model Context Protocol. 40 debugging tools for Claude Code and Claude Desktop.
Author-email: FYTJ <simonzhuyb@163.com>
License: MIT
Project-URL: Homepage, https://github.com/FYTJ/lldb-mcp-server
Project-URL: Repository, https://github.com/FYTJ/lldb-mcp-server.git
Project-URL: Documentation, https://github.com/FYTJ/lldb-mcp-server#readme
Project-URL: Issues, https://github.com/FYTJ/lldb-mcp-server/issues
Keywords: lldb,mcp,debugging,claude,anthropic,debugger
Classifier: Development Status :: 4 - Beta
Classifier: Intended Audience :: Developers
Classifier: License :: OSI Approved :: MIT License
Classifier: Operating System :: MacOS
Classifier: Operating System :: Microsoft :: Windows
Classifier: Operating System :: POSIX :: Linux
Classifier: Programming Language :: Python :: 3.10
Classifier: Programming Language :: Python :: 3.11
Classifier: Programming Language :: Python :: 3.12
Classifier: Programming Language :: Python :: 3.13
Classifier: Topic :: Software Development :: Debuggers
Requires-Python: >=3.10
Requires-Dist: fastmcp<3,>=2.0.0; python_version >= "3.10"
Requires-Dist: orjson>=3.11.4
Requires-Dist: pydantic>=2.12.5
Requires-Dist: typing-extensions>=4.15.0
Provides-Extra: dev
Requires-Dist: mypy>=1.18.2; extra == "dev"
Requires-Dist: pytest<9,>=8.0.0; extra == "dev"
Requires-Dist: pytest-cov>=4.1.0; extra == "dev"
Requires-Dist: pytest-asyncio>=0.21.0; extra == "dev"
Requires-Dist: ruff>=0.14.6; extra == "dev"
